python203/__init__.py
python203/backtestevaluator.py
python203/Tokentransfers.py
python203/volumebacktest.py
python203-0.1.4.dist-info/AUTHORS.rst
python203-0.1.4.dist-info/LICENSE
python203-0.1.4.dist-info/METADATA
python203-0.1.4.dist-info/WHEEL
python203-0.1.4.dist-info/RECORD
