Metadata-Version: 2.3
Name: python203
Version: 0.1.4
Summary: Python project as part of the Python Programming course taught by Juan Imbett in the Master 203 program at Paris Dauphine-PSL University.
License: MIT
Author: Maxime
Author-email: max70990@gmail.com
Requires-Python: >=3.8
Classifier: License :: OSI Approved :: MIT License
Classifier: Programming Language :: Python :: 3
Classifier: Programming Language :: Python :: 3.8
Classifier: Programming Language :: Python :: 3.9
Classifier: Programming Language :: Python :: 3.10
Classifier: Programming Language :: Python :: 3.11
Classifier: Programming Language :: Python :: 3.12
Classifier: Programming Language :: Python :: 3.13
Requires-Dist: typer (>=0.4.0,<0.5.0)
